{
    "name": "The Batman",
    "tmdb_id": "414906",
    "imdb_id": "tt1877830",
    "movieposter": [
        {
            "id": "363579",
            "url": "http://assets.fanart.tv/fanart/movies/414906/movieposter/the-batman-623a47ba3158c.jpg",
            "lang": "en",
            "likes": "9"
        },
        {
            "id": "358861",
            "url": "http://assets.fanart.tv/fanart/movies/414906/movieposter/the-batman-61f7b7d140d5d.jpg",
            "lang": "ru",
            "likes": "5"
        },
        {
            "id": "359912",
            "url": "http://assets.fanart.tv/fanart/movies/414906/movieposter/the-batman-6208f14b6d856.jpg",
            "lang": "en",
            "likes": "4"
        },
        {
            "id": "363578",
            "url": "http://assets.fanart.tv/fanart/movies/414906/movieposter/the-batman-623a47b6d9e2c.jpg",
            "lang": "en",
            "likes": "4"
        },
        {
            "id": "358395",
            "url": "http://assets.fanart.tv/fanart/movies/414906/movieposter/the-batman-61f013ac0f482.jpg",
            "lang": "ru",
            "likes": "4"
        },
        {
            "id": "363433",
            "url": "http://assets.fanart.tv/fanart/movies/414906/movieposter/the-batman-6239b20c7863a.jpg",
            "lang": "00",
            "likes": "4"
        },
        {
            "id": "363580",
            "url": "http://assets.fanart.tv/fanart/movies/414906/movieposter/the-batman-623a47be7fee2.jpg",
            "lang": "en",
            "likes": "4"
        },
        {
            "id": "363581",
            "url": "http://assets.fanart.tv/fanart/movies/414906/movieposter/the-batman-623a47c1181ad.jpg",
            "lang": "en",
            "likes": "4"
        },
        {
            "id": "308386",
            "url": "http://assets.fanart.tv/fanart/movies/414906/movieposter/the-batman-5f431be51d87b.jpg",
            "lang": "00",
            "likes": "4"
        },
        {
            "id": "348762",
            "url": "http://assets.fanart.tv/fanart/movies/414906/movieposter/the-batman-616ac0017d9fa.jpg",
            "lang": "en",
            "likes": "3"
        },
        {
            "id": "364201",
            "url": "http://assets.fanart.tv/fanart/movies/414906/movieposter/the-batman-624178dbe6ed7.jpg",
            "lang": "hu",
            "likes": "1"
        },
        {
            "id": "366441",
            "url": "http://assets.fanart.tv/fanart/movies/414906/movieposter/the-batman-625e54a2ed5da.jpg",
            "lang": "pl",
            "likes": "1"
        },
        {
            "id": "372567",
            "url": "http://assets.fanart.tv/fanart/movies/414906/movieposter/the-batman-62d849f2e186b.jpg",
            "lang": "en",
            "likes": "1"
        },
        {
            "id": "377000",
            "url": "http://assets.fanart.tv/fanart/movies/414906/movieposter/the-batman-632d19665f25b.jpg",
            "lang": "en",
            "likes": "1"
        },
        {
            "id": "308608",
            "url": "http://assets.fanart.tv/fanart/movies/414906/movieposter/the-batman-5f468d7a5078b.jpg",
            "lang": "00",
            "likes": "1"
        },
        {
            "id": "363188",
            "url": "http://assets.fanart.tv/fanart/movies/414906/movieposter/the-batman-6237738614f8f.jpeg",
            "lang": "00",
            "likes": "1"
        },
        {
            "id": "348685",
            "url": "http://assets.fanart.tv/fanart/movies/414906/movieposter/the-batman-6169b5241bd99.jpg",
            "lang": "00",
            "likes": "1"
        },
        {
            "id": "357870",
            "url": "http://assets.fanart.tv/fanart/movies/414906/movieposter/the-batman-61eab8540c8d8.jpg",
            "lang": "00",
            "likes": "1"
        },
        {
            "id": "361252",
            "url": "http://assets.fanart.tv/fanart/movies/414906/movieposter/the-batman-621cb62647d38.jpg",
            "lang": "00",
            "likes": "1"
        },
        {
            "id": "360654",
            "url": "http://assets.fanart.tv/fanart/movies/414906/movieposter/the-batman-621433096c1b5.jpg",
            "lang": "00",
            "likes": "1"
        },
        {
            "id": "359058",
            "url": "http://assets.fanart.tv/fanart/movies/414906/movieposter/the-batman-61f9d509ea80c.jpg",
            "lang": "en",
            "likes": "1"
        },
        {
            "id": "359057",
            "url": "http://assets.fanart.tv/fanart/movies/414906/movieposter/the-batman-61f9d507b23f0.jpg",
            "lang": "en",
            "likes": "1"
        },
        {
            "id": "366442",
            "url": "http://assets.fanart.tv/fanart/movies/414906/movieposter/the-batman-625e54b7834b1.jpg",
            "lang": "00",
            "likes": "0"
        },
        {
            "id": "366444",
            "url": "http://assets.fanart.tv/fanart/movies/414906/movieposter/the-batman-625e55e40fb9f.jpg",
            "lang": "00",
            "likes": "0"
        },
        {
            "id": "366447",
            "url": "http://assets.fanart.tv/fanart/movies/414906/movieposter/the-batman-625e70e584e56.jpg",
            "lang": "",
            "likes": "0"
        },
        {
            "id": "376998",
            "url": "http://assets.fanart.tv/fanart/movies/414906/movieposter/the-batman-632d1929c96b7.jpg",
            "lang": "00",
            "likes": "0"
        },
        {
            "id": "361275",
            "url": "http://assets.fanart.tv/fanart/movies/414906/movieposter/the-batman-621cf0cf384a5.jpg",
            "lang": "xx",
            "likes": "0"
        }
    ],
    "hdmovielogo": [
        {
            "id": "308160",
            "url": "http://assets.fanart.tv/fanart/movies/414906/hdmovielogo/the-batman-5f406d6c93339.png",
            "lang": "en",
            "likes": "8"
        },
        {
            "id": "363576",
            "url": "http://assets.fanart.tv/fanart/movies/414906/hdmovielogo/the-batman-623a46ce34015.png",
            "lang": "en",
            "likes": "7"
        },
        {
            "id": "317693",
            "url": "http://assets.fanart.tv/fanart/movies/414906/hdmovielogo/the-batman-5fde26ac201f4.png",
            "lang": "ru",
            "likes": "7"
        },
        {
            "id": "363574",
            "url": "http://assets.fanart.tv/fanart/movies/414906/hdmovielogo/the-batman-623a46c71027a.png",
            "lang": "en",
            "likes": "6"
        },
        {
            "id": "363575",
            "url": "http://assets.fanart.tv/fanart/movies/414906/hdmovielogo/the-batman-623a46ca075a5.png",
            "lang": "en",
            "likes": "6"
        },
        {
            "id": "364200",
            "url": "http://assets.fanart.tv/fanart/movies/414906/hdmovielogo/the-batman-624178c56df7f.png",
            "lang": "hu",
            "likes": "2"
        },
        {
            "id": "370415",
            "url": "http://assets.fanart.tv/fanart/movies/414906/hdmovielogo/the-batman-62b1d5cbf31ab.png",
            "lang": "en",
            "likes": "2"
        },
        {
            "id": "371347",
            "url": "http://assets.fanart.tv/fanart/movies/414906/hdmovielogo/the-batman-62c1916de1cff.png",
            "lang": "zh",
            "likes": "0"
        },
        {
            "id": "375636",
            "url": "http://assets.fanart.tv/fanart/movies/414906/hdmovielogo/the-batman-63149c0e3c71b.png",
            "lang": "hi",
            "likes": "0"
        }
    ],
    "moviedisc": [
        {
            "id": "360894",
            "url": "http://assets.fanart.tv/fanart/movies/414906/moviedisc/the-batman-6216c5ea8bf88.png",
            "lang": "en",
            "likes": "8",
            "disc": "1",
            "disc_type": "bluray"
        },
        {
            "id": "395424",
            "url": "http://assets.fanart.tv/fanart/movies/414906/moviedisc/the-batman-6463cad0756ed.png",
            "lang": "en",
            "likes": "6",
            "disc": "1",
            "disc_type": "uhd-bluray"
        },
        {
            "id": "358399",
            "url": "http://assets.fanart.tv/fanart/movies/414906/moviedisc/the-batman-61f02595332e6.png",
            "lang": "en",
            "likes": "4",
            "disc": "1",
            "disc_type": "bluray"
        },
        {
            "id": "349192",
            "url": "http://assets.fanart.tv/fanart/movies/414906/moviedisc/the-batman-616ecf76d7fff.png",
            "lang": "en",
            "likes": "4",
            "disc": "1",
            "disc_type": "bluray"
        },
        {
            "id": "363611",
            "url": "http://assets.fanart.tv/fanart/movies/414906/moviedisc/the-batman-623aa1e259c8f.png",
            "lang": "en",
            "likes": "1",
            "disc": "1",
            "disc_type": "bluray"
        },
        {
            "id": "340835",
            "url": "http://assets.fanart.tv/fanart/movies/414906/moviedisc/the-batman-60fba60cda889.png",
            "lang": "en",
            "likes": "0",
            "disc": "1",
            "disc_type": "bluray"
        }
    ],
    "hdmovieclearart": [
        {
            "id": "363435",
            "url": "http://assets.fanart.tv/fanart/movies/414906/hdmovieclearart/the-batman-6239b2336d297.png",
            "lang": "en",
            "likes": "6"
        },
        {
            "id": "395425",
            "url": "http://assets.fanart.tv/fanart/movies/414906/hdmovieclearart/the-batman-6463dcfa8528c.png",
            "lang": "en",
            "likes": "5"
        },
        {
            "id": "363604",
            "url": "http://assets.fanart.tv/fanart/movies/414906/hdmovieclearart/the-batman-623a69e98bc4b.png",
            "lang": "en",
            "likes": "5"
        },
        {
            "id": "360434",
            "url": "http://assets.fanart.tv/fanart/movies/414906/hdmovieclearart/the-batman-621132a044268.png",
            "lang": "en",
            "likes": "4"
        },
        {
            "id": "363648",
            "url": "http://assets.fanart.tv/fanart/movies/414906/hdmovieclearart/the-batman-623b23b57da76.png",
            "lang": "en",
            "likes": "4"
        },
        {
            "id": "360435",
            "url": "http://assets.fanart.tv/fanart/movies/414906/hdmovieclearart/the-batman-621132cc3bccf.png",
            "lang": "ru",
            "likes": "3"
        },
        {
            "id": "363436",
            "url": "http://assets.fanart.tv/fanart/movies/414906/hdmovieclearart/the-batman-6239b2462ee69.png",
            "lang": "ru",
            "likes": "3"
        },
        {
            "id": "360680",
            "url": "http://assets.fanart.tv/fanart/movies/414906/hdmovieclearart/the-batman-6214835fcd673.png",
            "lang": "en",
            "likes": "3"
        }
    ],
    "moviebackground": [
        {
            "id": "360681",
            "url": "http://assets.fanart.tv/fanart/movies/414906/moviebackground/the-batman-621483913d7df.jpg",
            "lang": "",
            "likes": "5"
        },
        {
            "id": "363434",
            "url": "http://assets.fanart.tv/fanart/movies/414906/moviebackground/the-batman-6239b21bc2486.jpg",
            "lang": "",
            "likes": "5"
        },
        {
            "id": "309018",
            "url": "http://assets.fanart.tv/fanart/movies/414906/moviebackground/the-batman-5f4c2cee8d600.jpg",
            "lang": "",
            "likes": "2"
        },
        {
            "id": "362842",
            "url": "http://assets.fanart.tv/fanart/movies/414906/moviebackground/the-batman-6234100e8a197.jpg",
            "lang": "",
            "likes": "2"
        },
        {
            "id": "289983",
            "url": "http://assets.fanart.tv/fanart/movies/414906/moviebackground/the-batman-5e6036bf564d5.jpg",
            "lang": "",
            "likes": "1"
        },
        {
            "id": "334294",
            "url": "http://assets.fanart.tv/fanart/movies/414906/moviebackground/the-batman-60a536e1d9922.jpg",
            "lang": "",
            "likes": "1"
        },
        {
            "id": "289982",
            "url": "http://assets.fanart.tv/fanart/movies/414906/moviebackground/the-batman-5e60368d245e6.jpg",
            "lang": "",
            "likes": "1"
        },
        {
            "id": "308282",
            "url": "http://assets.fanart.tv/fanart/movies/414906/moviebackground/the-batman-5f41d8295fdd5.jpg",
            "lang": "",
            "likes": "1"
        },
        {
            "id": "308453",
            "url": "http://assets.fanart.tv/fanart/movies/414906/moviebackground/the-batman-5f44497669595.jpg",
            "lang": "",
            "likes": "1"
        },
        {
            "id": "348694",
            "url": "http://assets.fanart.tv/fanart/movies/414906/moviebackground/the-batman-6169cb976886d.jpg",
            "lang": "",
            "likes": "1"
        },
        {
            "id": "362005",
            "url": "http://assets.fanart.tv/fanart/movies/414906/moviebackground/the-batman-6228815b185f8.jpg",
            "lang": "",
            "likes": "1"
        },
        {
            "id": "361205",
            "url": "http://assets.fanart.tv/fanart/movies/414906/moviebackground/the-batman-621c1184f1767.jpg",
            "lang": "",
            "likes": "1"
        },
        {
            "id": "359915",
            "url": "http://assets.fanart.tv/fanart/movies/414906/moviebackground/the-batman-6208f56140e5c.jpg",
            "lang": "",
            "likes": "1"
        },
        {
            "id": "356155",
            "url": "http://assets.fanart.tv/fanart/movies/414906/moviebackground/the-batman-61cf47cf3eebe.jpg",
            "lang": "",
            "likes": "1"
        },
        {
            "id": "308611",
            "url": "http://assets.fanart.tv/fanart/movies/414906/moviebackground/the-batman-5f468e541558b.jpg",
            "lang": "",
            "likes": "0"
        },
        {
            "id": "366363",
            "url": "http://assets.fanart.tv/fanart/movies/414906/moviebackground/the-batman-625d3c703cd07.jpg",
            "lang": "",
            "likes": "0"
        },
        {
            "id": "290130",
            "url": "http://assets.fanart.tv/fanart/movies/414906/moviebackground/the-batman-5e62bf2a6d1e9.jpg",
            "lang": "",
            "likes": "0"
        }
    ],
    "moviebanner": [
        {
            "id": "364202",
            "url": "http://assets.fanart.tv/fanart/movies/414906/moviebanner/the-batman-624178f6dc2ca.jpg",
            "lang": "hu",
            "likes": "2"
        },
        {
            "id": "348767",
            "url": "http://assets.fanart.tv/fanart/movies/414906/moviebanner/the-batman-616ad7348fea5.jpg",
            "lang": "en",
            "likes": "1"
        },
        {
            "id": "369266",
            "url": "http://assets.fanart.tv/fanart/movies/414906/moviebanner/the-batman-629b376f270ad.jpg",
            "lang": "en",
            "likes": "0"
        },
        {
            "id": "308283",
            "url": "http://assets.fanart.tv/fanart/movies/414906/moviebanner/the-batman-5f41d84de5658.jpg",
            "lang": "en",
            "likes": "0"
        }
    ],
    "moviethumb": [
        {
            "id": "308284",
            "url": "http://assets.fanart.tv/fanart/movies/414906/moviethumb/the-batman-5f41d86cadc1f.jpg",
            "lang": "en",
            "likes": "2"
        },
        {
            "id": "364203",
            "url": "http://assets.fanart.tv/fanart/movies/414906/moviethumb/the-batman-6241790971382.jpg",
            "lang": "hu",
            "likes": "1"
        },
        {
            "id": "308286",
            "url": "http://assets.fanart.tv/fanart/movies/414906/moviethumb/the-batman-5f41da0f24d6d.jpg",
            "lang": "en",
            "likes": "1"
        },
        {
            "id": "348766",
            "url": "http://assets.fanart.tv/fanart/movies/414906/moviethumb/the-batman-616ad6ae6c862.jpg",
            "lang": "en",
            "likes": "1"
        },
        {
            "id": "363610",
            "url": "http://assets.fanart.tv/fanart/movies/414906/moviethumb/the-batman-623aa1c88fc60.jpg",
            "lang": "en",
            "likes": "0"
        },
        {
            "id": "366446",
            "url": "http://assets.fanart.tv/fanart/movies/414906/moviethumb/the-batman-625e6faf82069.jpg",
            "lang": "pl",
            "likes": "0"
        },
        {
            "id": "363609",
            "url": "http://assets.fanart.tv/fanart/movies/414906/moviethumb/the-batman-623aa1c3ed732.jpg",
            "lang": "en",
            "likes": "0"
        }
    ]
}