<?xml version="1.0" encoding="utf-8"?><episode id="241193" update="2021-07-19">
<epno type="1">3</epno>
<length>25</length>
<airdate>2021-06-19</airdate>
<rating votes="6">6.51</rating>
<title xml:lang="ja">坊ちゃんと満月の流星群</title>
<title xml:lang="en">The Duke and the Meteor Shower During the Full Moon</title>
<title xml:lang="x-jat">Bocchan to Mangetsu no Ryuuseigun</title>
<summary>After losing a bet to Alice, the Duke agrees to take her to the town’s masquerade festival. But the two get separated when the Duke, clad in a clunky, steel costume to protect others from his touch of death, gets carried away by the crowd…
Source: Funimation</summary>
<resources>
<resource type="28">
<externalentity>
<identifier>G7PU4053N</identifier>
</externalentity>
</resource>
</resources>
</episode>